README.md
setup.cfg
setup.py
distributions/Binomialdistribution.py
distributions/Gaussiandistribution.py
distributions/Generaldistribution.py
distributions/__init__.py
ngandn18_dist.egg-info/PKG-INFO
ngandn18_dist.egg-info/SOURCES.txt
ngandn18_dist.egg-info/dependency_links.txt
ngandn18_dist.egg-info/not-zip-safe
ngandn18_dist.egg-info/top_level.txt