Metadata-Version: 2.1
Name: ngandn18-dist
Version: 0.3
Summary: Gaussian & Binomial distributions
Home-page: UNKNOWN
Author: Thien Ngan Doan
Author-email: ngandn18@gmail.com
License: UNKNOWN
Platform: UNKNOWN
Classifier: Programming Language :: Python :: 3
Classifier: License :: OSI Approved :: MIT License
Classifier: Operating System :: OS Independent
Requires-Python: >=3.6
